decodebin-0.2.1.dist-info/METADATA
decodebin-0.2.1.dist-info/WHEEL
decodebin/__init__.py
decodebin/decodebin.cp310-win_amd64.pyd
decodebin-0.2.1.dist-info/RECORD
